ChangeLog
INSTALL
LICENSE
NEWS
README
ez_setup.py
setup.py
docs/AUTHORS
docs/BUGS
docs/DEVEL.txt
docs/TODO
docs/europython2005.mgp
docs/profiling.py
docs/pywifi.tpp
docs/pywifi_english.tpp
examples/pyiwconfig.py
examples/pyiwlist.py
python_wifi.egg-info/PKG-INFO
python_wifi.egg-info/SOURCES.txt
python_wifi.egg-info/dependency_links.txt
python_wifi.egg-info/top_level.txt
pythonwifi/__init__.py
pythonwifi/flags.py
pythonwifi/iwlibs.py
tests/README
tests/test_wireless.py
tests/test_wireless_doctest.py
