Metadata-Version: 1.0
Name: python-wifi
Version: 0.3.1
Summary: Python-Wifi is a Python library that provides access to information
Home-page: https://developer.berlios.de/projects/pythonwifi/
Author: Róman Joost
Author-email: roman@bromeco.de
License: LGPL
Download-URL: https://developer.berlios.de/projects/pythonwifi/
Keywords: wifi wireless wlan iwconfig iwtools
Platform: UNKNOWN
Classifier: Environment :: Console
Classifier: Intended Audience :: Developers
Classifier: License :: OSI Approved :: GNU Library or Lesser General Public License (LGPL)
Classifier: Operating System :: POSIX :: Linux
Classifier: Programming Language :: Python
Classifier: Topic :: System :: Networking
